example/demo.py
example/test_userAliUid_python.py
wobs/file_trace.py
wobs/observer.py
wobs/trackpoint.py
wobs/userInfo.py
wobs-0.1.6.dist-info/METADATA
wobs-0.1.6.dist-info/WHEEL
wobs-0.1.6.dist-info/top_level.txt
wobs-0.1.6.dist-info/RECORD
