Metadata-Version: 2.4
Name: wobs
Version: 0.1.6
Summary: Wuying Observer SDK for Python
Requires-Python: >=3.9
Requires-Dist: opentelemetry-api>=1.36.0
Requires-Dist: opentelemetry-sdk>=1.36.0
Requires-Dist: pytest>=8.4.2
